README.md
setup.cfg
setup.py
liberty/__init__.py
liberty/async_http_server.py
liberty/http_server.py
liberty.py.egg-info/PKG-INFO
liberty.py.egg-info/SOURCES.txt
liberty.py.egg-info/dependency_links.txt
liberty.py.egg-info/top_level.txt