Metadata-Version: 2.1
Name: liberty.py
Version: 1.0.3
Summary: Library for creating web servers.
Home-page: https://github.com/xXxCLOTIxXx/liberty
Author: Xsarz
Author-email: xsarzy@gmail.com
License: MIT
Download-URL: https://github.com/xXxCLOTIxXx/liberty/archive/refs/heads/main.zip
Keywords: web,server,networksapi,python,python3,python3.x,xsarz,official
Platform: UNKNOWN
